avishan/__init__.py
avishan/installation.txt
avishan/middlewares.py
avishan/requirements.txt
avishan/stage.py
avishan/utils.py
avishan/views.py
avishan/__pycache__/__init__.cpython-37.pyc
avishan/__pycache__/middlewares.cpython-37.pyc
avishan/__pycache__/stage.cpython-37.pyc
avishan/__pycache__/utils.cpython-37.pyc
avishan/__pycache__/views.cpython-37.pyc
falcon_avishan-0.0.2.dist-info/LICENSE
falcon_avishan-0.0.2.dist-info/METADATA
falcon_avishan-0.0.2.dist-info/WHEEL
falcon_avishan-0.0.2.dist-info/top_level.txt
falcon_avishan-0.0.2.dist-info/RECORD
